mywigle/__init__.py
mywigle/config.py
mywigle/fileuploads.py
mywigle/http.py
mywigle/network.py
mywigle/profile.py
mywigle/sniffer.py
mywigle/stats.py
mywigle-0.3.0.dist-info/LICENSE
mywigle-0.3.0.dist-info/METADATA
mywigle-0.3.0.dist-info/WHEEL
mywigle-0.3.0.dist-info/RECORD
