Metadata-Version: 2.3
Name: mywigle
Version: 0.3.0
Summary: mywigle is a wrapper for the WiGLE WiFi mapping API
Author: tct123
Author-email: 42028373+tct123@users.noreply.github.com
Requires-Python: >=3.8
Classifier: Programming Language :: Python :: 3
Classifier: Programming Language :: Python :: 3.8
Classifier: Programming Language :: Python :: 3.9
Classifier: Programming Language :: Python :: 3.10
Classifier: Programming Language :: Python :: 3.11
Classifier: Programming Language :: Python :: 3.12
Classifier: Programming Language :: Python :: 3.13
Requires-Dist: requests (>=2.32.3,<3.0.0)
